{"@type":"Flow","@id":"9d29d276-ee6f-44a3-ac14-a81a47a4efdb","name":"Ether, 2,2,3,3,3-Pentafluoropropyl methyl-, HFE-365mcf3","category":"Elementary flows/Emission to air/low population density","version":"00.00.000","flowType":"ELEMENTARY_FLOW","cas":"000378-16-5","isInfrastructureFlow":false,"flowProperties":[{"@type":"FlowPropertyFactor","isRefFlowProperty":true,"flowProperty":{"@type":"FlowProperty","@id":"93a60a56-a3c8-11da-a746-0800200b9a66","name":"Mass","category":"Technical flow properties","refUnit":"kg"},"conversionFactor":1.0}]}